mielophone/__init__.py
mielophone/util/__init__.py
mielophone-0.1.dist-info/LICENSE
mielophone-0.1.dist-info/METADATA
mielophone-0.1.dist-info/WHEEL
mielophone-0.1.dist-info/top_level.txt
mielophone-0.1.dist-info/RECORD
